[
  {
    "amount": -46.54,
    "payee": "Walmart",
    "description": "Bathroom parts",
    "account_id": "account_1766289004108_7ps0slg4g",
    "category_id": "category_1766288771747_qek6wlmy8",
    "cleared": true,
    "date": "2025-01-01",
    "id": "expense_import_1767473622536_3i18df07k",
    "created_at": "2026-01-03T20:53:42.536Z"
  },
  {
    "amount": -34.95,
    "id": "expense_import_1767473622536_d5mdphdgt",
    "created_at": "2026-01-03T20:53:42.536Z",
    "description": "",
    "category_id": "category_1766265357718_y7lydlt9a",
    "date": "2025-01-01",
    "cleared": true,
    "account_id": "account_1766289004108_7ps0slg4g",
    "payee": "Centracom"
  },
  {
    "amount": -20.64,
    "cleared": true,
    "id": "expense_import_1767473622536_qxqk37kxb",
    "description": "",
    "category_id": "category_1766288816655_pee1xcbk6",
    "account_id": "account_1766289004108_7ps0slg4g",
    "payee": "chick fil a",
    "date": "2025-01-04",
    "created_at": "2026-01-03T20:53:42.536Z"
  },
  {
    "payee": "Deseret Book",
    "description": "Scriptures",
    "id": "expense_import_1767473622536_7z8rn59hc",
    "category_id": "category_1766288825592_glvgzh2u4",
    "created_at": "2026-01-03T20:53:42.536Z",
    "amount": -66,
    "date": "2025-01-04",
    "account_id": "account_1766289004108_7ps0slg4g",
    "cleared": true
  },
  {
    "description": "Scriptures and Books",
    "payee": "Deseret Book",
    "id": "expense_import_1767473622536_s5pbtk2js",
    "cleared": true,
    "date": "2025-01-04",
    "category_id": "category_1766288743633_wkkcxygrr",
    "amount": -100,
    "account_id": "account_1766289004108_7ps0slg4g",
    "created_at": "2026-01-03T20:53:42.536Z"
  },
  {
    "payee": "Spotify",
    "cleared": true,
    "account_id": "account_1766289004108_7ps0slg4g",
    "category_id": "category_1766265351648_ru851obn1",
    "id": "expense_import_1767473622536_ps68e5jb8",
    "description": "",
    "amount": -11.81,
    "date": "2025-01-04",
    "created_at": "2026-01-03T20:53:42.536Z"
  },
  {
    "created_at": "2026-01-03T20:53:42.536Z",
    "id": "expense_import_1767473622536_wscw1xvv1",
    "category_id": "Zfr8EwlTWLmsk7vYirAT",
    "amount": -3590.09,
    "date": "2025-01-04",
    "account_id": "IO0iUrZNOLB125YrvUaF",
    "payee": "Mr. Cooper Mortgage",
    "cleared": true,
    "description": ""
  },
  {
    "date": "2025-01-04",
    "description": "",
    "id": "expense_import_1767473622536_302by4uyz",
    "payee": "Venmo",
    "cleared": true,
    "created_at": "2026-01-03T20:53:42.536Z",
    "category_id": "category_1766288825592_glvgzh2u4",
    "amount": -6,
    "account_id": "IO0iUrZNOLB125YrvUaF"
  },
  {
    "payee": "Vanguard",
    "description": "",
    "category_id": "category_1766288765095_ew8htogil",
    "date": "2025-01-06",
    "amount": -1166.74,
    "account_id": "IO0iUrZNOLB125YrvUaF",
    "cleared": true,
    "id": "expense_import_1767473622536_vyf58ge2j",
    "created_at": "2026-01-03T20:53:42.536Z"
  },
  {
    "account_id": "account_1766289004108_7ps0slg4g",
    "amount": 15,
    "cleared": true,
    "date": "2025-01-06",
    "id": "expense_import_1767473622536_ml0e2hg5c",
    "created_at": "2026-01-03T20:53:42.536Z",
    "description": "",
    "payee": "Canyon View Medical",
    "category_id": "category_1766288615238_l94bjlz89"
  },
  {
    "account_id": "account_1766289004108_7ps0slg4g",
    "date": "2025-01-07",
    "cleared": true,
    "description": "",
    "created_at": "2026-01-03T20:53:42.536Z",
    "category_id": "category_1766265369105_ehvqlgukb",
    "amount": -35,
    "payee": "McKell",
    "id": "expense_import_1767473622536_4bcnydhf5"
  },
  {
    "date": "2025-01-07",
    "payee": "Government (Utah)",
    "cleared": true,
    "amount": -132.5,
    "id": "expense_import_1767473622536_k1a3r5f48",
    "created_at": "2026-01-03T20:53:42.536Z",
    "category_id": "category_1766265369105_ehvqlgukb",
    "account_id": "account_1766289015844_afauk11gp",
    "description": ""
  },
  {
    "cleared": true,
    "description": "",
    "created_at": "2026-01-03T20:53:42.536Z",
    "amount": -25,
    "category_id": "category_1766288746550_763eaiy62",
    "payee": "Venmo",
    "id": "expense_import_1767473622536_kwhoxwcns",
    "date": "2025-01-09",
    "account_id": "IO0iUrZNOLB125YrvUaF"
  },
  {
    "created_at": "2026-01-03T20:53:42.536Z",
    "date": "2025-01-07",
    "payee": "Church of Jesus Christ",
    "id": "expense_import_1767473622536_v4t02hzj6",
    "account_id": "IO0iUrZNOLB125YrvUaF",
    "category_id": "69LUQGMJrYlIPoixIkng",
    "cleared": true,
    "amount": -1215.87,
    "description": ""
  },
  {
    "account_id": "IO0iUrZNOLB125YrvUaF",
    "category_id": "lvRJzTnpe7HkaAzJwmOn",
    "cleared": true,
    "description": "",
    "amount": -40,
    "created_at": "2026-01-03T20:53:42.536Z",
    "payee": "Church of Jesus Christ",
    "date": "2025-01-07",
    "id": "expense_import_1767473622536_1o565yasg"
  },
  {
    "description": "",
    "category_id": "category_1766265437406_yihi892i4",
    "account_id": "account_1766289004108_7ps0slg4g",
    "amount": -5.58,
    "created_at": "2026-01-03T20:53:42.536Z",
    "date": "2025-01-09",
    "id": "expense_import_1767473622536_95qc3gzv0",
    "payee": "Conoco",
    "cleared": true
  },
  {
    "category_id": "category_1766265437406_yihi892i4",
    "account_id": "account_1766289004108_7ps0slg4g",
    "amount": -29.62,
    "cleared": true,
    "payee": "Conoco",
    "date": "2025-01-09",
    "created_at": "2026-01-03T20:53:42.536Z",
    "id": "expense_import_1767473622536_b8v9m113t",
    "description": ""
  },
  {
    "account_id": "account_1766289004108_7ps0slg4g",
    "created_at": "2026-01-03T20:53:42.536Z",
    "category_id": "category_1766265437406_yihi892i4",
    "date": "2025-01-09",
    "amount": -23.8,
    "id": "expense_import_1767473622536_1ccdvdka4",
    "payee": "Costco",
    "cleared": true,
    "description": ""
  },
  {
    "description": "",
    "created_at": "2026-01-03T20:53:42.536Z",
    "cleared": true,
    "payee": "Costco",
    "date": "2025-01-09",
    "category_id": "pPQqTWxWz4IjeHW5Z1iX",
    "account_id": "account_1766289004108_7ps0slg4g",
    "amount": -187.61,
    "id": "expense_import_1767473622536_k9eay4z57"
  },
  {
    "cleared": true,
    "id": "expense_import_1767473622536_j11wp7uv0",
    "category_id": "category_1766288625999_zpi9ppeqw",
    "description": "Treadmill",
    "account_id": "account_1766289015844_afauk11gp",
    "amount": -2156.48,
    "payee": "Costco",
    "date": "2025-01-11",
    "created_at": "2026-01-03T20:53:42.536Z"
  },
  {
    "description": "",
    "category_id": "pPQqTWxWz4IjeHW5Z1iX",
    "id": "expense_import_1767473622536_1uf384new",
    "created_at": "2026-01-03T20:53:42.536Z",
    "amount": -142.49,
    "payee": "Walmart",
    "date": "2025-01-15",
    "cleared": true,
    "account_id": "account_1766289015844_afauk11gp"
  },
  {
    "category_id": "category_1766265357718_y7lydlt9a",
    "account_id": "IO0iUrZNOLB125YrvUaF",
    "cleared": true,
    "id": "expense_import_1767473622536_w993itps3",
    "amount": -108.67,
    "date": "2025-01-15",
    "payee": "Dominion Energy",
    "created_at": "2026-01-03T20:53:42.536Z",
    "description": ""
  },
  {
    "payee": "Amazon",
    "cleared": true,
    "id": "expense_import_1767473622536_n1dj6j5n4",
    "created_at": "2026-01-03T20:53:42.536Z",
    "amount": -24.09,
    "account_id": "account_1766289004108_7ps0slg4g",
    "date": "2025-01-11",
    "category_id": "category_1766265357718_y7lydlt9a",
    "description": "16.76+7.33 DVD, Bibb, Gloves"
  },
  {
    "payee": "Lowe's",
    "cleared": true,
    "category_id": "category_1766288816655_pee1xcbk6",
    "account_id": "account_1766289004108_7ps0slg4g",
    "description": "Penny Trampoline Park",
    "created_at": "2026-01-03T20:53:42.536Z",
    "amount": -4.84,
    "date": "2025-01-16",
    "id": "expense_import_1767473622536_cosixfl9b"
  },
  {
    "date": "2025-01-16",
    "description": "Books and Birthday",
    "category_id": "category_1766265357718_y7lydlt9a",
    "created_at": "2026-01-03T20:53:42.536Z",
    "id": "expense_import_1767473622536_unl8dg71h",
    "account_id": "account_1766289015844_afauk11gp",
    "payee": "Amazon",
    "amount": -35.89,
    "cleared": true
  },
  {
    "account_id": "account_1766289015844_afauk11gp",
    "category_id": "pPQqTWxWz4IjeHW5Z1iX",
    "cleared": true,
    "payee": "Walmart",
    "amount": -41.22,
    "id": "expense_import_1767473622536_pd5znslne",
    "created_at": "2026-01-03T20:53:42.536Z",
    "date": "2025-01-20",
    "description": "Clocks"
  },
  {
    "account_id": "account_1766289004108_7ps0slg4g",
    "cleared": true,
    "payee": "Walmart",
    "id": "expense_import_1767473622536_fjmao4dpm",
    "category_id": "pPQqTWxWz4IjeHW5Z1iX",
    "created_at": "2026-01-03T20:53:42.536Z",
    "amount": -38.5,
    "description": "",
    "date": "2025-01-20"
  },
  {
    "created_at": "2026-01-03T20:53:42.536Z",
    "account_id": "account_1766289004108_7ps0slg4g",
    "date": "2025-01-21",
    "payee": "Google Fi",
    "id": "expense_import_1767473622536_zky918dxo",
    "category_id": "category_1766265357718_y7lydlt9a",
    "cleared": true,
    "amount": -51.28,
    "description": ""
  },
  {
    "payee": "Amazon",
    "account_id": "account_1766289015844_afauk11gp",
    "category_id": "category_1766265357718_y7lydlt9a",
    "amount": 9.66,
    "date": "2025-01-22",
    "id": "expense_import_1767473622536_70irfzrsp",
    "created_at": "2026-01-03T20:53:42.536Z",
    "cleared": true,
    "description": "Refund"
  },
  {
    "account_id": "account_1766289015844_afauk11gp",
    "payee": "Amazon",
    "description": "Refund",
    "created_at": "2026-01-03T20:53:42.536Z",
    "category_id": "pPQqTWxWz4IjeHW5Z1iX",
    "amount": 17.18,
    "cleared": true,
    "id": "expense_import_1767473622536_5royrrb5f",
    "date": "2025-01-22"
  },
  {
    "id": "expense_import_1767473622536_5cih1u6tc",
    "account_id": "account_1766289004108_7ps0slg4g",
    "description": "Utilities",
    "cleared": true,
    "amount": -235.95,
    "date": "2025-01-28",
    "category_id": "category_1766265357718_y7lydlt9a",
    "created_at": "2026-01-03T20:53:42.536Z",
    "payee": "Payson Utilities"
  },
  {
    "created_at": "2026-01-03T20:53:42.536Z",
    "description": "",
    "id": "expense_import_1767473622536_8d2girbgm",
    "date": "2025-01-24",
    "payee": "Costco",
    "category_id": "pPQqTWxWz4IjeHW5Z1iX",
    "account_id": "account_1766289004108_7ps0slg4g",
    "amount": -143.45,
    "cleared": true
  },
  {
    "id": "expense_import_1767473622536_y7yl6eubr",
    "amount": -62.18,
    "account_id": "account_1766289015844_afauk11gp",
    "description": "",
    "cleared": true,
    "date": "2025-01-24",
    "payee": "Walmart",
    "created_at": "2026-01-03T20:53:42.536Z",
    "category_id": "pPQqTWxWz4IjeHW5Z1iX"
  },
  {
    "id": "expense_import_1767473622536_84rq50sih",
    "category_id": "category_1766288829038_0ygxsees9",
    "description": "Penny Fabric",
    "account_id": "account_1766289015844_afauk11gp",
    "amount": -148.67,
    "created_at": "2026-01-03T20:53:42.536Z",
    "payee": "JoAnn's",
    "cleared": true,
    "date": "2025-01-24"
  },
  {
    "amount": -51.76,
    "cleared": true,
    "description": "",
    "payee": "Amazon",
    "account_id": "account_1766289004108_7ps0slg4g",
    "category_id": "category_1766288743633_wkkcxygrr",
    "id": "expense_import_1767473622536_9lks1uu6g",
    "date": "2025-01-25",
    "created_at": "2026-01-03T20:53:42.536Z"
  },
  {
    "date": "2025-01-25",
    "id": "expense_import_1767473622536_54giwdh4n",
    "description": "",
    "cleared": true,
    "account_id": "account_1766289004108_7ps0slg4g",
    "category_id": "category_1766288816655_pee1xcbk6",
    "created_at": "2026-01-03T20:53:42.536Z",
    "amount": -13,
    "payee": "Provo Rec Center"
  },
  {
    "created_at": "2026-01-03T20:53:42.536Z",
    "category_id": "category_1766288816655_pee1xcbk6",
    "date": "2025-01-25",
    "id": "expense_import_1767473622536_nxjzbf6os",
    "description": "",
    "account_id": "account_1766289004108_7ps0slg4g",
    "payee": "chick fil a",
    "amount": -32.43,
    "cleared": true
  },
  {
    "id": "expense_import_1767473622536_3fj7afaxc",
    "date": "2025-01-25",
    "cleared": true,
    "category_id": "pPQqTWxWz4IjeHW5Z1iX",
    "account_id": "account_1766289015844_afauk11gp",
    "payee": "Credit",
    "created_at": "2026-01-03T20:53:42.536Z",
    "description": "",
    "amount": 36.57
  },
  {
    "created_at": "2026-01-03T20:53:42.536Z",
    "date": "2025-01-25",
    "id": "expense_import_1767473622536_jwafvcm81",
    "account_id": "account_1766289015844_afauk11gp",
    "description": "",
    "category_id": "pPQqTWxWz4IjeHW5Z1iX",
    "cleared": true,
    "payee": "Walmart",
    "amount": -88.71
  },
  {
    "created_at": "2026-01-03T20:53:42.536Z",
    "payee": "Aumni",
    "description": "Tithing",
    "id": "expense_import_1767473622536_1pfnx5u7r",
    "cleared": true,
    "amount": 1974,
    "account_id": "IO0iUrZNOLB125YrvUaF",
    "category_id": "69LUQGMJrYlIPoixIkng",
    "date": "2025-01-28"
  },
  {
    "id": "expense_import_1767473622536_ophumyve8",
    "cleared": true,
    "created_at": "2026-01-03T20:53:42.536Z",
    "account_id": "IO0iUrZNOLB125YrvUaF",
    "date": "2025-01-28",
    "payee": "Aumni",
    "category_id": "category_1766288743633_wkkcxygrr",
    "description": "",
    "amount": 2500
  },
  {
    "date": "2025-01-28",
    "description": "",
    "id": "expense_import_1767473622536_r6ldprm1i",
    "amount": 2500,
    "cleared": true,
    "category_id": "category_1766265047006_n028ssip1",
    "payee": "Aumni",
    "created_at": "2026-01-03T20:53:42.536Z",
    "account_id": "IO0iUrZNOLB125YrvUaF"
  },
  {
    "cleared": true,
    "id": "expense_import_1767473622536_m92xy9uhu",
    "amount": 11600,
    "payee": "Aumni",
    "category_id": "category_1766288625999_zpi9ppeqw",
    "created_at": "2026-01-03T20:53:42.536Z",
    "account_id": "IO0iUrZNOLB125YrvUaF",
    "date": "2025-01-28",
    "description": ""
  },
  {
    "cleared": true,
    "amount": 50,
    "created_at": "2026-01-03T20:53:42.536Z",
    "description": "",
    "id": "expense_import_1767473622536_2dddup0dm",
    "date": "2025-01-28",
    "account_id": "IO0iUrZNOLB125YrvUaF",
    "payee": "Aumni",
    "category_id": "category_1766288825592_glvgzh2u4"
  },
  {
    "amount": 50,
    "payee": "Aumni",
    "id": "expense_import_1767473622536_y79egu5no",
    "cleared": true,
    "account_id": "IO0iUrZNOLB125YrvUaF",
    "created_at": "2026-01-03T20:53:42.536Z",
    "date": "2025-01-28",
    "description": "",
    "category_id": "category_1766288829038_0ygxsees9"
  },
  {
    "date": "2025-01-28",
    "account_id": "IO0iUrZNOLB125YrvUaF",
    "category_id": "pPQqTWxWz4IjeHW5Z1iX",
    "payee": "Aumni",
    "amount": 66,
    "created_at": "2026-01-03T20:53:42.536Z",
    "description": "",
    "id": "expense_import_1767473622536_9srq6mmiw",
    "cleared": true
  },
  {
    "cleared": true,
    "description": "",
    "date": "2025-01-28",
    "account_id": "IO0iUrZNOLB125YrvUaF",
    "id": "expense_import_1767473622536_3plithbfr",
    "amount": 1000,
    "created_at": "2026-01-03T20:53:42.536Z",
    "category_id": "category_1766288738225_b60g12x67",
    "payee": "Aumni"
  },
  {
    "created_at": "2026-01-03T20:53:42.536Z",
    "cleared": true,
    "category_id": "category_1766265357718_y7lydlt9a",
    "account_id": "account_1766289004108_7ps0slg4g",
    "description": "",
    "payee": "Utopia Fiber",
    "id": "expense_import_1767473622536_l5kjytsa4",
    "amount": -30,
    "date": "2025-01-28"
  },
  {
    "created_at": "2026-01-03T20:53:42.536Z",
    "account_id": "account_1766289004108_7ps0slg4g",
    "description": "",
    "id": "expense_import_1767473622536_npa3uyn48",
    "date": "2025-01-29",
    "payee": "Hangtime",
    "category_id": "category_1766288816655_pee1xcbk6",
    "amount": -6.44,
    "cleared": true
  },
  {
    "id": "expense_import_1767473622536_b0do8m9ev",
    "description": "Piggyback Rider, Ear Protection",
    "category_id": "category_1766265047006_n028ssip1",
    "date": "2025-01-30",
    "payee": "Amazon",
    "created_at": "2026-01-03T20:53:42.536Z",
    "cleared": true,
    "amount": -292.22,
    "account_id": "account_1766289015844_afauk11gp"
  },
  {
    "payee": "Walmart",
    "created_at": "2026-01-03T20:53:42.536Z",
    "date": "2025-01-31",
    "description": "",
    "id": "expense_import_1767473622536_x40o7uvnh",
    "account_id": "account_1766289004108_7ps0slg4g",
    "category_id": "pPQqTWxWz4IjeHW5Z1iX",
    "cleared": true,
    "amount": -97.75
  }
]