[
  {
    "adjustments": -2168.85,
    "expenses": -5610.69,
    "net_change": 2722.89,
    "income": 10502.43,
    "account_id": "IO0iUrZNOLB125YrvUaF",
    "start_balance": 47118.21,
    "end_balance": 49841.1,
    "transfers": 0
  },
  {
    "end_balance": 4807.64,
    "net_change": 0.2,
    "expenses": 0,
    "income": 0.2,
    "start_balance": 4807.44,
    "transfers": 0,
    "adjustments": 0,
    "account_id": "account_1766289996367_pzpaad94s"
  },
  {
    "transfers": 0,
    "net_change": 91.87,
    "account_id": "account_1766289015844_afauk11gp",
    "adjustments": 947.66,
    "start_balance": -1660.32,
    "expenses": -855.79,
    "end_balance": -1568.45,
    "income": 0
  },
  {
    "start_balance": -876.83,
    "account_id": "account_1766289004108_7ps0slg4g",
    "income": 0,
    "expenses": -1823.01,
    "end_balance": -1478.65,
    "adjustments": 1221.19,
    "transfers": 0,
    "net_change": -601.82
  },
  {
    "adjustments": 0,
    "expenses": 0,
    "income": 0,
    "transfers": 0,
    "net_change": 0,
    "start_balance": 2713.33,
    "account_id": "FR91hqtm3olrgHn8aYDt",
    "end_balance": 2713.33
  },
  {
    "adjustments": 0,
    "start_balance": 32441.32,
    "net_change": 0,
    "transfers": 0,
    "expenses": 0,
    "end_balance": 32441.32,
    "account_id": "account_1766290102117_4e04nppj6",
    "income": 0
  },
  {
    "net_change": 0,
    "transfers": 0,
    "start_balance": 25715.85,
    "income": 0,
    "end_balance": 25715.85,
    "account_id": "account_1766290329121_fzxbijeyi",
    "expenses": 0,
    "adjustments": 0
  },
  {
    "end_balance": 10666.68,
    "net_change": 0,
    "account_id": "account_1766290334872_jf0ix8swh",
    "start_balance": 10666.68,
    "income": 0,
    "transfers": 0,
    "adjustments": 0,
    "expenses": 0
  },
  {
    "account_id": "account_hidden_1767678803953_alerus",
    "transfers": 0,
    "end_balance": 14877.86,
    "expenses": 0,
    "net_change": 0,
    "income": 0,
    "start_balance": 14877.86,
    "adjustments": 0
  },
  {
    "transfers": 0,
    "expenses": 0,
    "start_balance": 450.84,
    "account_id": "account_1766290108085_f863835t0",
    "adjustments": 0,
    "income": 0,
    "net_change": 0,
    "end_balance": 450.84
  },
  {
    "expenses": 0,
    "end_balance": 5937.77,
    "account_id": "account_1766290117504_3753hwck6",
    "adjustments": 0,
    "start_balance": 5937.77,
    "transfers": 0,
    "income": 0,
    "net_change": 0
  }
]