[
  {
    "cleared": true,
    "created_at": "2026-01-03T20:53:42.532Z",
    "id": "expense_import_1767473622532_y1zrwflu5",
    "amount": -104.13,
    "payee": "Walmart",
    "date": "2023-01-04",
    "category_id": "pPQqTWxWz4IjeHW5Z1iX",
    "description": "",
    "account_id": "account_1766289015844_afauk11gp"
  },
  {
    "id": "expense_import_1767473622532_ss3fm4hn1",
    "category_id": "category_1766288829038_0ygxsees9",
    "cleared": true,
    "amount": -37.98,
    "payee": "Amazon",
    "created_at": "2026-01-03T20:53:42.532Z",
    "description": "Shoes",
    "account_id": "account_1766289015844_afauk11gp",
    "date": "2023-01-04"
  },
  {
    "id": "expense_import_1767473622532_m3f71ttpx",
    "amount": -12.64,
    "category_id": "category_1766288829038_0ygxsees9",
    "cleared": true,
    "date": "2023-01-09",
    "account_id": "account_1766289015844_afauk11gp",
    "created_at": "2026-01-03T20:53:42.532Z",
    "payee": "Chubby's",
    "description": "Lunch"
  },
  {
    "id": "expense_import_1767473622532_8yny3jmpa",
    "date": "2023-01-09",
    "cleared": true,
    "description": "Renewal",
    "created_at": "2026-01-03T20:53:42.532Z",
    "account_id": "account_1766289015844_afauk11gp",
    "payee": "DMV",
    "category_id": "category_1766265369105_ehvqlgukb",
    "amount": -150
  },
  {
    "account_id": "account_1766289996367_pzpaad94s",
    "description": "",
    "amount": 50,
    "payee": "Momkins",
    "category_id": "category_1766288829038_0ygxsees9",
    "created_at": "2026-01-03T20:53:42.532Z",
    "cleared": true,
    "date": "2023-01-09",
    "id": "expense_import_1767473622532_69a4etbng"
  },
  {
    "amount": -300,
    "account_id": "FR91hqtm3olrgHn8aYDt",
    "date": "2023-01-07",
    "created_at": "2026-01-03T20:53:42.532Z",
    "id": "expense_import_1767473622532_8d1do1thz",
    "payee": "Momkins",
    "cleared": true,
    "description": "Emergency cash",
    "category_id": "category_1766265047006_n028ssip1"
  },
  {
    "date": "2023-01-02",
    "account_id": "account_1766289004108_7ps0slg4g",
    "payee": "Mod Pizza",
    "category_id": "category_1766288816655_pee1xcbk6",
    "amount": -13.01,
    "id": "expense_import_1767473622532_06k95l770",
    "description": "",
    "created_at": "2026-01-03T20:53:42.532Z",
    "cleared": true
  },
  {
    "category_id": "category_1766265351648_ru851obn1",
    "date": "2023-01-03",
    "description": "",
    "id": "expense_import_1767473622532_94chk29ee",
    "payee": "Spotify",
    "created_at": "2026-01-03T20:53:42.532Z",
    "account_id": "account_1766289004108_7ps0slg4g",
    "amount": -10.71,
    "cleared": true
  },
  {
    "account_id": "account_1766289004108_7ps0slg4g",
    "date": "2023-01-03",
    "payee": "Amazon",
    "created_at": "2026-01-03T20:53:42.532Z",
    "amount": -0.5,
    "category_id": "category_1766288825592_glvgzh2u4",
    "cleared": true,
    "id": "expense_import_1767473622532_k4qz5c28l",
    "description": ""
  },
  {
    "category_id": "pPQqTWxWz4IjeHW5Z1iX",
    "description": "",
    "created_at": "2026-01-03T20:53:42.532Z",
    "cleared": true,
    "account_id": "account_1766289004108_7ps0slg4g",
    "date": "2023-01-03",
    "amount": -10.69,
    "id": "expense_import_1767473622532_qr77tqwsm",
    "payee": "Walmart"
  },
  {
    "id": "expense_import_1767473622532_0fe3c5e8d",
    "amount": -34.95,
    "category_id": "category_1766265357718_y7lydlt9a",
    "cleared": true,
    "payee": "Centracom",
    "date": "2023-01-04",
    "created_at": "2026-01-03T20:53:42.532Z",
    "account_id": "account_1766289004108_7ps0slg4g",
    "description": ""
  },
  {
    "created_at": "2026-01-03T20:53:42.532Z",
    "category_id": "category_1766265369105_ehvqlgukb",
    "cleared": true,
    "description": "",
    "date": "2023-01-09",
    "payee": "Tire Busters",
    "id": "expense_import_1767473622532_92egwps4r",
    "amount": -40,
    "account_id": "account_1766289004108_7ps0slg4g"
  },
  {
    "category_id": "category_1766265369105_ehvqlgukb",
    "id": "expense_import_1767473622532_spli5f52g",
    "payee": "Carquest",
    "cleared": true,
    "description": "",
    "date": "2023-01-09",
    "amount": -72.68,
    "account_id": "account_1766289004108_7ps0slg4g",
    "created_at": "2026-01-03T20:53:42.532Z"
  },
  {
    "id": "expense_import_1767473622532_ve3iym1bx",
    "account_id": "account_1766289004108_7ps0slg4g",
    "payee": "Taco Bell",
    "description": "",
    "amount": -12.54,
    "created_at": "2026-01-03T20:53:42.532Z",
    "category_id": "category_1766288825592_glvgzh2u4",
    "date": "2023-01-09",
    "cleared": true
  },
  {
    "description": "Shelves",
    "account_id": "IO0iUrZNOLB125YrvUaF",
    "amount": -25,
    "date": "2023-01-03",
    "id": "expense_import_1767473622532_orlutc079",
    "created_at": "2026-01-03T20:53:42.532Z",
    "cleared": true,
    "payee": "Venmo",
    "category_id": "category_1766288743633_wkkcxygrr"
  },
  {
    "category_id": "category_1766288743633_wkkcxygrr",
    "cleared": true,
    "amount": -25,
    "created_at": "2026-01-03T20:53:42.532Z",
    "id": "expense_import_1767473622532_4xtzehym7",
    "account_id": "IO0iUrZNOLB125YrvUaF",
    "description": "Shelves",
    "date": "2023-01-03",
    "payee": "Venmo"
  },
  {
    "category_id": "category_1766288625999_zpi9ppeqw",
    "cleared": true,
    "payee": "Venmo",
    "amount": -150,
    "description": "Benches",
    "id": "expense_import_1767473622532_e255tym4e",
    "account_id": "IO0iUrZNOLB125YrvUaF",
    "date": "2023-01-03",
    "created_at": "2026-01-03T20:53:42.532Z"
  },
  {
    "account_id": "IO0iUrZNOLB125YrvUaF",
    "payee": "United Wholesale Mortgage",
    "category_id": "Zfr8EwlTWLmsk7vYirAT",
    "cleared": true,
    "date": "2023-01-03",
    "description": "Mortgage",
    "id": "expense_import_1767473622532_9a1ha0mho",
    "amount": -3446.21,
    "created_at": "2026-01-03T20:53:42.532Z"
  },
  {
    "amount": -1083.48,
    "category_id": "category_1766288765095_ew8htogil",
    "date": "2023-01-03",
    "id": "expense_import_1767473622532_ahr1g8unq",
    "cleared": true,
    "account_id": "IO0iUrZNOLB125YrvUaF",
    "description": "Roth, $541.74 x2",
    "created_at": "2026-01-03T20:53:42.532Z",
    "payee": "Vanguard"
  },
  {
    "cleared": true,
    "description": "Lunch with coworkers",
    "amount": -22.5,
    "id": "expense_import_1767473622532_iy3mecoze",
    "account_id": "IO0iUrZNOLB125YrvUaF",
    "date": "2023-01-09",
    "category_id": "category_1766288825592_glvgzh2u4",
    "payee": "Venmo",
    "created_at": "2026-01-03T20:53:42.532Z"
  },
  {
    "amount": -150,
    "description": "Couches",
    "cleared": true,
    "date": "2023-01-09",
    "payee": "Venmo",
    "id": "expense_import_1767473622532_dglkpxcj2",
    "account_id": "IO0iUrZNOLB125YrvUaF",
    "created_at": "2026-01-03T20:53:42.532Z",
    "category_id": "category_1766265357718_y7lydlt9a"
  },
  {
    "date": "2023-01-12",
    "created_at": "2026-01-03T20:53:42.532Z",
    "id": "expense_import_1767473622532_e5mk0mm2f",
    "account_id": "account_1766289015844_afauk11gp",
    "category_id": "pPQqTWxWz4IjeHW5Z1iX",
    "payee": "Walmart",
    "cleared": true,
    "description": "",
    "amount": -107.88
  },
  {
    "amount": 6.77,
    "cleared": true,
    "id": "expense_import_1767473622532_0r88q4ji5",
    "account_id": "account_1766289015844_afauk11gp",
    "date": "2023-01-12",
    "created_at": "2026-01-03T20:53:42.532Z",
    "description": "",
    "payee": "Wal",
    "category_id": "pPQqTWxWz4IjeHW5Z1iX"
  },
  {
    "id": "expense_import_1767473622532_tw92j2j3t",
    "created_at": "2026-01-03T20:53:42.532Z",
    "category_id": "category_1766265047006_n028ssip1",
    "description": "",
    "payee": "walmart",
    "amount": -39.9,
    "date": "2023-01-13",
    "cleared": true,
    "account_id": "account_1766289015844_afauk11gp"
  },
  {
    "created_at": "2026-01-03T20:53:42.532Z",
    "account_id": "account_1766289015844_afauk11gp",
    "category_id": "pPQqTWxWz4IjeHW5Z1iX",
    "date": "2023-01-16",
    "id": "expense_import_1767473622532_6m860sqsa",
    "cleared": true,
    "payee": "Walmart",
    "description": "",
    "amount": -10.17
  },
  {
    "date": "2023-01-17",
    "description": "",
    "category_id": "category_1766288816655_pee1xcbk6",
    "created_at": "2026-01-03T20:53:42.532Z",
    "cleared": true,
    "amount": -15.45,
    "payee": "Crumbl",
    "account_id": "account_1766289015844_afauk11gp",
    "id": "expense_import_1767473622532_t6d76wyan"
  },
  {
    "description": "Sewing Machine",
    "id": "expense_import_1767473622532_unr68h3c5",
    "created_at": "2026-01-03T20:53:42.532Z",
    "amount": -409.49,
    "payee": "Joann",
    "cleared": true,
    "date": "2023-01-19",
    "account_id": "account_1766289015844_afauk11gp",
    "category_id": "category_1766288829038_0ygxsees9"
  },
  {
    "cleared": true,
    "created_at": "2026-01-03T20:53:42.532Z",
    "payee": "Brighton",
    "date": "2023-01-11",
    "amount": -195.05,
    "id": "expense_import_1767473622532_i17q3b7qt",
    "description": "Skii",
    "category_id": "category_1766288825592_glvgzh2u4",
    "account_id": "account_1766289004108_7ps0slg4g"
  },
  {
    "amount": -27.01,
    "created_at": "2026-01-03T20:53:42.532Z",
    "category_id": "category_1766288816655_pee1xcbk6",
    "date": "2023-01-12",
    "account_id": "account_1766289004108_7ps0slg4g",
    "description": "",
    "cleared": true,
    "id": "expense_import_1767473622532_ib7cqvc8f",
    "payee": "Better Bowls"
  },
  {
    "account_id": "account_1766289004108_7ps0slg4g",
    "description": "",
    "date": "2023-01-12",
    "created_at": "2026-01-03T20:53:42.532Z",
    "amount": -25.07,
    "payee": "Chevron",
    "id": "expense_import_1767473622532_6egr44xsq",
    "cleared": true,
    "category_id": "category_1766265437406_yihi892i4"
  },
  {
    "id": "expense_import_1767473622532_b7w9yncnd",
    "date": "2023-01-13",
    "description": "",
    "created_at": "2026-01-03T20:53:42.532Z",
    "account_id": "account_1766289004108_7ps0slg4g",
    "cleared": true,
    "payee": "In-N-Out",
    "amount": -8.34,
    "category_id": "category_1766288825592_glvgzh2u4"
  },
  {
    "created_at": "2026-01-03T20:53:42.532Z",
    "category_id": "category_1766288625999_zpi9ppeqw",
    "payee": "Ace",
    "account_id": "account_1766289004108_7ps0slg4g",
    "description": "",
    "date": "2023-01-16",
    "amount": -1.82,
    "cleared": true,
    "id": "expense_import_1767473622532_e4w22c7k2"
  },
  {
    "amount": -9.18,
    "id": "expense_import_1767473622532_ju99kw1il",
    "date": "2023-01-16",
    "category_id": "category_1766288743633_wkkcxygrr",
    "created_at": "2026-01-03T20:53:42.532Z",
    "account_id": "account_1766289004108_7ps0slg4g",
    "cleared": true,
    "payee": "Amazon",
    "description": ""
  },
  {
    "category_id": "category_1766288833773_gbqpud8im",
    "date": "2023-01-16",
    "description": "The Chosen",
    "cleared": true,
    "created_at": "2026-01-03T20:53:42.532Z",
    "account_id": "account_1766289004108_7ps0slg4g",
    "id": "expense_import_1767473622532_fu716ut0y",
    "amount": -20.6,
    "payee": "Come & See Foundation"
  },
  {
    "cleared": true,
    "payee": "Dominion Energy",
    "created_at": "2026-01-03T20:53:42.532Z",
    "date": "2023-01-17",
    "id": "expense_import_1767473622532_13h0w73k9",
    "account_id": "IO0iUrZNOLB125YrvUaF",
    "amount": -126.03,
    "category_id": "category_1766265357718_y7lydlt9a",
    "description": ""
  },
  {
    "cleared": true,
    "created_at": "2026-01-03T20:53:42.532Z",
    "category_id": "69LUQGMJrYlIPoixIkng",
    "account_id": "IO0iUrZNOLB125YrvUaF",
    "id": "expense_import_1767473622532_xbg96z8lc",
    "payee": "Church of Jesus Christ",
    "amount": -1012.22,
    "description": "",
    "date": "2023-01-18"
  },
  {
    "account_id": "IO0iUrZNOLB125YrvUaF",
    "category_id": "lvRJzTnpe7HkaAzJwmOn",
    "id": "expense_import_1767473622532_67j8whjq7",
    "description": "",
    "cleared": true,
    "payee": "Church of Jesus Christ",
    "created_at": "2026-01-03T20:53:42.532Z",
    "amount": -40,
    "date": "2023-01-18"
  },
  {
    "created_at": "2026-01-03T20:53:42.532Z",
    "description": "Reilly Refund",
    "date": "2023-01-19",
    "account_id": "IO0iUrZNOLB125YrvUaF",
    "category_id": "category_1766288825592_glvgzh2u4",
    "payee": "Venmo",
    "id": "expense_import_1767473622532_rmgx8yjjk",
    "cleared": true,
    "amount": 80
  },
  {
    "created_at": "2026-01-03T20:53:42.532Z",
    "id": "expense_import_1767473622532_v5n1bms9e",
    "description": "",
    "cleared": true,
    "date": "2023-01-21",
    "account_id": "account_1766289004108_7ps0slg4g",
    "category_id": "category_1766265357718_y7lydlt9a",
    "payee": "Google Fi",
    "amount": -66.8
  },
  {
    "description": "Extra Payment",
    "payee": "Unit",
    "category_id": "Zfr8EwlTWLmsk7vYirAT",
    "date": "2023-01-20",
    "id": "expense_import_1767473622532_ilda6gn0p",
    "cleared": true,
    "account_id": "IO0iUrZNOLB125YrvUaF",
    "created_at": "2026-01-03T20:53:42.532Z",
    "amount": -1267
  },
  {
    "description": "",
    "created_at": "2026-01-03T20:53:42.532Z",
    "cleared": true,
    "account_id": "account_1766289015844_afauk11gp",
    "payee": "Dollar Tree",
    "date": "2023-01-21",
    "amount": -20.01,
    "category_id": "category_1766288743633_wkkcxygrr",
    "id": "expense_import_1767473622532_j5o5viw6o"
  },
  {
    "cleared": true,
    "category_id": "pPQqTWxWz4IjeHW5Z1iX",
    "id": "expense_import_1767473622532_nbpmyp41g",
    "description": "Groceries",
    "created_at": "2026-01-03T20:53:42.532Z",
    "date": "2023-01-23",
    "payee": "Walmart",
    "account_id": "account_1766289015844_afauk11gp",
    "amount": -169.8
  },
  {
    "created_at": "2026-01-03T20:53:42.532Z",
    "account_id": "account_1766289004108_7ps0slg4g",
    "category_id": "category_1766288816655_pee1xcbk6",
    "date": "2023-01-23",
    "description": "Tickets",
    "payee": "Hale Theatre",
    "cleared": true,
    "amount": -138,
    "id": "expense_import_1767473622532_twhqj8yfe"
  },
  {
    "payee": "Intermountain Healthcare",
    "amount": -616,
    "category_id": "category_1766288615238_l94bjlz89",
    "created_at": "2026-01-03T20:53:42.532Z",
    "description": "Stitches",
    "account_id": "account_1766289004108_7ps0slg4g",
    "cleared": true,
    "id": "expense_import_1767473622532_m8zietcpg",
    "date": "2023-01-24"
  },
  {
    "date": "2023-01-25",
    "account_id": "account_1766289004108_7ps0slg4g",
    "amount": -17.53,
    "cleared": true,
    "id": "expense_import_1767473622532_1vyklg4kt",
    "category_id": "category_1766265437406_yihi892i4",
    "payee": "Chevron",
    "description": "",
    "created_at": "2026-01-03T20:53:42.532Z"
  },
  {
    "cleared": true,
    "date": "2023-01-28",
    "created_at": "2026-01-03T20:53:42.532Z",
    "payee": "Utopia Fiber",
    "category_id": "category_1766265357718_y7lydlt9a",
    "account_id": "account_1766289004108_7ps0slg4g",
    "amount": -30,
    "id": "expense_import_1767473622532_l6afsltbo",
    "description": "Internet"
  },
  {
    "cleared": true,
    "payee": "Utilities",
    "description": "",
    "amount": -225.41,
    "account_id": "account_1766289004108_7ps0slg4g",
    "id": "expense_import_1767473622532_c57nvgr9l",
    "date": "2023-01-28",
    "created_at": "2026-01-03T20:53:42.532Z",
    "category_id": "category_1766265357718_y7lydlt9a"
  },
  {
    "id": "expense_import_1767473622532_i1xr2z7jd",
    "cleared": true,
    "created_at": "2026-01-03T20:53:42.532Z",
    "description": "",
    "payee": "Venmo",
    "date": "2023-01-27",
    "account_id": "IO0iUrZNOLB125YrvUaF",
    "amount": -15,
    "category_id": "category_1766288743633_wkkcxygrr"
  },
  {
    "created_at": "2026-01-03T20:53:42.532Z",
    "amount": -38.6,
    "account_id": "account_1766289015844_afauk11gp",
    "description": "",
    "id": "expense_import_1767473622532_iygs69euu",
    "payee": "Amazon",
    "cleared": true,
    "category_id": "category_1766288743633_wkkcxygrr",
    "date": "2023-01-27"
  },
  {
    "payee": "Walmart",
    "cleared": true,
    "date": "2023-01-30",
    "category_id": "pPQqTWxWz4IjeHW5Z1iX",
    "created_at": "2026-01-03T20:53:42.532Z",
    "amount": 8.16,
    "description": "Refund stupid eggs",
    "account_id": "account_1766289015844_afauk11gp",
    "id": "expense_import_1767473622532_2i9tfmlov"
  },
  {
    "description": "",
    "date": "2023-01-31",
    "account_id": "account_1766289015844_afauk11gp",
    "id": "expense_import_1767473622532_exmk284z1",
    "amount": -48.83,
    "category_id": "category_1766265437406_yihi892i4",
    "cleared": true,
    "payee": "Chevron",
    "created_at": "2026-01-03T20:53:42.532Z"
  }
]